{"trial_id": "0154", "hyperparameters": {"space": [{"class_name": "Int", "config": {"name": "hidden_layers", "default": null, "conditions": [], "min_value": 4, "max_value": 7, "step": 1, "sampling": "linear"}}, {"class_name": "Fixed", "config": {"name": "learning_rate", "conditions": [], "value": 0.001526017960390335}}, {"class_name": "Fixed", "config": {"name": "batch_size", "conditions": [], "value": 16}}, {"class_name": "Fixed", "config": {"name": "batch_norm", "conditions": [], "value": false}}, {"class_name": "Boolean", "config": {"name": "dropout", "default": false, "conditions": []}}, {"class_name": "Float", "config": {"name": "do_rate", "default": 0.2, "conditions": [], "min_value": 0.1, "max_value": 0.5, "step": null, "sampling": "linear"}}, {"class_name": "Int", "config": {"name": "units_1", "default": null, "conditions": [], "min_value": 16, "max_value": 114, "step": 32, "sampling": "linear"}}, {"class_name": "Int", "config": {"name": "units_2", "default": null, "conditions": [], "min_value": 16, "max_value": 114, "step": 32, "sampling": "linear"}}, {"class_name": "Int", "config": {"name": "units_3", "default": null, "conditions": [], "min_value": 16, "max_value": 114, "step": 32, "sampling": "linear"}}, {"class_name": "Int", "config": {"name": "units_4", "default": null, "conditions": [], "min_value": 16, "max_value": 114, "step": 32, "sampling": "linear"}}, {"class_name": "Int", "config": {"name": "units_5", "default": null, "conditions": [], "min_value": 16, "max_value": 114, "step": 32, "sampling": "linear"}}, {"class_name": "Int", "config": {"name": "units_6", "default": null, "conditions": [], "min_value": 16, "max_value": 114, "step": 32, "sampling": "linear"}}, {"class_name": "Int", "config": {"name": "units_7", "default": null, "conditions": [], "min_value": 16, "max_value": 114, "step": 32, "sampling": "linear"}}], "values": {"hidden_layers": 4, "learning_rate": 0.001526017960390335, "batch_size": 16, "batch_norm": false, "dropout": true, "do_rate": 0.10530700888175293, "units_1": 112, "units_2": 112, "units_3": 16, "units_4": 112, "units_5": 16, "units_6": 112, "units_7": 112, "tuner/epochs": 4, "tuner/initial_epoch": 0, "tuner/bracket": 3, "tuner/round": 0}}, "metrics": {"metrics": {"loss": {"direction": "min", "observations": [{"value": [1.4460623264312744], "step": 2}]}, "accuracy": {"direction": "max", "observations": [{"value": [0.473503977060318], "step": 2}]}, "QuadraticWeightedKappa": {"direction": "min", "observations": [{"value": [0.4311424195766449], "step": 2}]}, "val_loss": {"direction": "min", "observations": [{"value": [1.4149905443191528], "step": 2}]}, "val_accuracy": {"direction": "max", "observations": [{"value": [0.48863252997398376], "step": 2}]}, "val_QuadraticWeightedKappa": {"direction": "min", "observations": [{"value": [0.4391721785068512], "step": 2}]}}}, "score": 0.48863252997398376, "best_step": 2, "status": "COMPLETED", "message": null}