{"trial_id": "0066", "hyperparameters": {"space": [{"class_name": "Fixed", "config": {"name": "learning_rate", "conditions": [], "value": 0.01894635097944879}}, {"class_name": "Fixed", "config": {"name": "batch_size", "conditions": [], "value": 64}}, {"class_name": "Fixed", "config": {"name": "batch_norm", "conditions": [], "value": true}}, {"class_name": "Fixed", "config": {"name": "dropout", "conditions": [], "value": false}}, {"class_name": "Fixed", "config": {"name": "dropout_rate", "conditions": [], "value": 0.2}}, {"class_name": "Int", "config": {"name": "hidden_layers", "default": null, "conditions": [], "min_value": 6, "max_value": 8, "step": 1, "sampling": "linear"}}, {"class_name": "Int", "config": {"name": "units_1", "default": null, "conditions": [], "min_value": 16, "max_value": 114, "step": 32, "sampling": "linear"}}, {"class_name": "Int", "config": {"name": "units_2", "default": null, "conditions": [], "min_value": 16, "max_value": 114, "step": 32, "sampling": "linear"}}, {"class_name": "Int", "config": {"name": "units_3", "default": null, "conditions": [], "min_value": 16, "max_value": 114, "step": 32, "sampling": "linear"}}, {"class_name": "Int", "config": {"name": "units_4", "default": null, "conditions": [], "min_value": 16, "max_value": 114, "step": 32, "sampling": "linear"}}, {"class_name": "Int", "config": {"name": "units_5", "default": null, "conditions": [], "min_value": 16, "max_value": 114, "step": 32, "sampling": "linear"}}, {"class_name": "Int", "config": {"name": "units_6", "default": null, "conditions": [], "min_value": 16, "max_value": 114, "step": 32, "sampling": "linear"}}, {"class_name": "Int", "config": {"name": "units_7", "default": null, "conditions": [], "min_value": 16, "max_value": 114, "step": 32, "sampling": "linear"}}, {"class_name": "Int", "config": {"name": "units_8", "default": null, "conditions": [], "min_value": 16, "max_value": 114, "step": 32, "sampling": "linear"}}], "values": {"learning_rate": 0.01894635097944879, "batch_size": 64, "batch_norm": true, "dropout": false, "dropout_rate": 0.2, "hidden_layers": 8, "units_1": 80, "units_2": 80, "units_3": 48, "units_4": 112, "units_5": 16, "units_6": 80, "units_7": 48, "units_8": 112, "tuner/epochs": 2, "tuner/initial_epoch": 0, "tuner/bracket": 4, "tuner/round": 0}}, "metrics": {"metrics": {"loss": {"direction": "min", "observations": [{"value": [1.4212720394134521], "step": 1}]}, "accuracy": {"direction": "max", "observations": [{"value": [0.480352520942688], "step": 1}]}, "QuadraticWeightedKappa": {"direction": "min", "observations": [{"value": [0.4600013792514801], "step": 1}]}, "val_loss": {"direction": "min", "observations": [{"value": [1.547005534172058], "step": 1}]}, "val_accuracy": {"direction": "max", "observations": [{"value": [0.44813069701194763], "step": 1}]}, "val_QuadraticWeightedKappa": {"direction": "min", "observations": [{"value": [0.5247088670730591], "step": 1}]}}}, "score": 0.44813069701194763, "best_step": 1, "status": "COMPLETED", "message": null}