{"trial_id": "0210", "hyperparameters": {"space": [{"class_name": "Fixed", "config": {"name": "batch_norm", "conditions": [], "value": false}}, {"class_name": "Fixed", "config": {"name": "hidden_layers", "conditions": [], "value": 1}}, {"class_name": "Fixed", "config": {"name": "units_1", "conditions": [], "value": 88}}, {"class_name": "Fixed", "config": {"name": "dropout", "conditions": [], "value": true}}, {"class_name": "Fixed", "config": {"name": "dropout_rate", "conditions": [], "value": 0.1}}, {"class_name": "Float", "config": {"name": "learning_rate", "default": 0.0001, "conditions": [], "min_value": 0.0001, "max_value": 0.1, "step": null, "sampling": "log"}}, {"class_name": "Choice", "config": {"name": "batch_size", "default": 32, "conditions": [], "values": [16, 32, 64, 128, 256, 512, 1024], "ordered": true}}], "values": {"batch_norm": false, "hidden_layers": 1, "units_1": 88, "dropout": true, "dropout_rate": 0.1, "learning_rate": 0.003270417513120582, "batch_size": 256, "tuner/epochs": 12, "tuner/initial_epoch": 0, "tuner/bracket": 2, "tuner/round": 0}}, "metrics": {"metrics": {"loss": {"direction": "min", "observations": [{"value": [0.17150458693504333], "step": 7}]}, "mean_absolute_error_labels": {"direction": "min", "observations": [{"value": [1.5914493799209595], "step": 7}]}, "val_loss": {"direction": "min", "observations": [{"value": [0.17232106626033783], "step": 7}]}, "val_mean_absolute_error_labels": {"direction": "min", "observations": [{"value": [1.5373038053512573], "step": 7}]}}}, "score": 1.5373038053512573, "best_step": 7, "status": "COMPLETED", "message": null}